src/openai_python_api/__init__.py
src/openai_python_api/chatgpt.py
src/openai_python_api/dalle.py
src/openai_python_api/gpt_statistics.py
src/openai_python_api/logger_config.py
src/openai_python_api/models.py
openai_python_api-0.1.0.dist-info/METADATA
openai_python_api-0.1.0.dist-info/WHEEL
openai_python_api-0.1.0.dist-info/licenses/LICENSE
openai_python_api-0.1.0.dist-info/RECORD
