Metadata-Version: 2.4
Name: openai_python_api
Version: 0.1.0
Summary: OpenAI Python API
Project-URL: Homepage, https://github.com/wwakabobik/openai_api
Project-URL: Bug Tracker, https://github.com/wwakabobik/openai_api/issues
Author-email: Iliya Vereshchagin <i.vereshchagin@gmail.com>
Maintainer-email: Iliya Vereshchagin <i.vereshchagin@gmail.com>
License: MIT License
License-File: LICENSE
Keywords: ai,api,artificial intelligence,chatgpt,dalle,dalle2,gpt,openai
Classifier: Intended Audience :: Developers
Classifier: Intended Audience :: Information Technology
Classifier: License :: OSI Approved :: MIT License
Classifier: Operating System :: OS Independent
Classifier: Programming Language :: Python :: 3.9
Classifier: Programming Language :: Python :: 3.10
Classifier: Programming Language :: Python :: 3.11
Classifier: Programming Language :: Python :: 3.12
Classifier: Programming Language :: Python :: 3.13
Classifier: Topic :: Scientific/Engineering :: Artificial Intelligence
Classifier: Topic :: Scientific/Engineering :: Human Machine Interfaces
Classifier: Topic :: Scientific/Engineering :: Image Processing
Classifier: Topic :: Scientific/Engineering :: Visualization
Classifier: Topic :: Software Development :: Libraries :: Python Modules
Requires-Python: >=3.9
Requires-Dist: aiofiles
Requires-Dist: aiohttp
Requires-Dist: async-timeout
Requires-Dist: asyncio
Requires-Dist: certifi
Requires-Dist: charset-normalizer
Requires-Dist: frozenlist
Requires-Dist: openai
Requires-Dist: pillow
Requires-Dist: requests
Requires-Dist: urllib3
